{
    "name": "Ampharos",
    "abilities": [
        "Static",
        "Plus"
    ],
    "types": [
        "electric"
    ],
    "stats": {
        "hp": 90,
        "atk": 75,
        "def": 85,
        "spa": 115,
        "spd": 90,
        "spe": 55
    },
    "moves": [
        {
            "name": "After You",
            "learnMethod": "level-up"
        },
        {
            "name": "Agility",
            "learnMethod": "machine"
        },
        {
            "name": "Body Slam",
            "learnMethod": "level-up"
        },
        {
            "name": "Brick Break",
            "learnMethod": "machine"
        },
        {
            "name": "Bulldoze",
            "learnMethod": "machine"
        },
        {
            "name": "Charge",
            "learnMethod": "level-up"
        },
        {
            "name": "Charge Beam",
            "learnMethod": "machine"
        },
        {
            "name": "Confuse Ray",
            "learnMethod": "level-up"
        },
        {
            "name": "Cotton Guard",
            "learnMethod": "level-up"
        },
        {
            "name": "Cotton Spore",
            "learnMethod": "level-up"
        },
        {
            "name": "Dazzling Gleam",
            "learnMethod": "level-up"
        },
        {
            "name": "Dig",
            "learnMethod": "machine"
        },
        {
            "name": "Discharge",
            "learnMethod": "level-up"
        },
        {
            "name": "Dragon Pulse",
            "learnMethod": "level-up"
        },
        {
            "name": "Dragon Tail",
            "learnMethod": "machine"
        },
        {
            "name": "Eerie Impulse",
            "learnMethod": "machine"
        },
        {
            "name": "Electric Terrain",
            "learnMethod": "machine"
        },
        {
            "name": "Electro Ball",
            "learnMethod": "level-up"
        },
        {
            "name": "Electroweb",
            "learnMethod": "level-up"
        },
        {
            "name": "Endure",
            "learnMethod": "level-up"
        },
        {
            "name": "Facade",
            "learnMethod": "machine"
        },
        {
            "name": "Fire Punch",
            "learnMethod": "level-up"
        },
        {
            "name": "Flatter",
            "learnMethod": "egg"
        },
        {
            "name": "Fling",
            "learnMethod": "machine"
        },
        {
            "name": "Focus Blast",
            "learnMethod": "machine"
        },
        {
            "name": "Giga Impact",
            "learnMethod": "machine"
        },
        {
            "name": "Growl",
            "learnMethod": "level-up"
        },
        {
            "name": "Helping Hand",
            "learnMethod": "machine"
        },
        {
            "name": "Hyper Beam",
            "learnMethod": "machine"
        },
        {
            "name": "Ice Punch",
            "learnMethod": "machine"
        },
        {
            "name": "Light Screen",
            "learnMethod": "level-up"
        },
        {
            "name": "Low Kick",
            "learnMethod": "machine"
        },
        {
            "name": "Magnetic Flux",
            "learnMethod": "level-up"
        },
        {
            "name": "Outrage",
            "learnMethod": "level-up"
        },
        {
            "name": "Power Gem",
            "learnMethod": "level-up"
        },
        {
            "name": "Protect",
            "learnMethod": "machine"
        },
        {
            "name": "Rain Dance",
            "learnMethod": "machine"
        },
        {
            "name": "Reflect",
            "learnMethod": "machine"
        },
        {
            "name": "Rest",
            "learnMethod": "machine"
        },
        {
            "name": "Sleep Talk",
            "learnMethod": "level-up"
        },
        {
            "name": "Stomping Tantrum",
            "learnMethod": "machine"
        },
        {
            "name": "Substitute",
            "learnMethod": "level-up"
        },
        {
            "name": "Sunny Day",
            "learnMethod": "machine"
        },
        {
            "name": "Swift",
            "learnMethod": "level-up"
        },
        {
            "name": "Tackle",
            "learnMethod": "level-up"
        },
        {
            "name": "Take Down",
            "learnMethod": "level-up"
        },
        {
            "name": "Tera Blast",
            "learnMethod": "machine"
        },
        {
            "name": "Thunder",
            "learnMethod": "level-up"
        },
        {
            "name": "Thunder Punch",
            "learnMethod": "level-up"
        },
        {
            "name": "Thunder Shock",
            "learnMethod": "level-up"
        },
        {
            "name": "Thunder Wave",
            "learnMethod": "level-up"
        },
        {
            "name": "Thunderbolt",
            "learnMethod": "level-up"
        },
        {
            "name": "Trailblaze",
            "learnMethod": "machine"
        },
        {
            "name": "Volt Switch",
            "learnMethod": "machine"
        },
        {
            "name": "Wild Charge",
            "learnMethod": "machine"
        },
        {
            "name": "Zap Cannon",
            "learnMethod": "level-up"
        }
    ]
}