{
    "name": "Cresselia",
    "abilities": [
        {
            "name": "Levitate",
            "hidden": false
        }
    ],
    "types": [
        "psychic"
    ],
    "stats": {
        "hp": 120,
        "atk": 70,
        "def": 110,
        "spa": 75,
        "spd": 120,
        "spe": 85
    },
    "moves": [
        {
            "name": "Ally Switch",
            "learnMethod": "level-up"
        },
        {
            "name": "Aurora Beam",
            "learnMethod": "level-up"
        },
        {
            "name": "Body Slam",
            "learnMethod": "machine"
        },
        {
            "name": "Calm Mind",
            "learnMethod": "machine"
        },
        {
            "name": "Charge Beam",
            "learnMethod": "machine"
        },
        {
            "name": "Confuse Ray",
            "learnMethod": "machine"
        },
        {
            "name": "Confusion",
            "learnMethod": "level-up"
        },
        {
            "name": "Dazzling Gleam",
            "learnMethod": "machine"
        },
        {
            "name": "Double Team",
            "learnMethod": "level-up"
        },
        {
            "name": "Endure",
            "learnMethod": "machine"
        },
        {
            "name": "Energy Ball",
            "learnMethod": "machine"
        },
        {
            "name": "Expanding Force",
            "learnMethod": "machine"
        },
        {
            "name": "Facade",
            "learnMethod": "machine"
        },
        {
            "name": "Future Sight",
            "learnMethod": "level-up"
        },
        {
            "name": "Giga Impact",
            "learnMethod": "machine"
        },
        {
            "name": "Grass Knot",
            "learnMethod": "machine"
        },
        {
            "name": "Gravity",
            "learnMethod": "machine"
        },
        {
            "name": "Helping Hand",
            "learnMethod": "machine"
        },
        {
            "name": "Hyper Beam",
            "learnMethod": "machine"
        },
        {
            "name": "Ice Beam",
            "learnMethod": "machine"
        },
        {
            "name": "Icy Wind",
            "learnMethod": "machine"
        },
        {
            "name": "Light Screen",
            "learnMethod": "machine"
        },
        {
            "name": "Lunar Blessing",
            "learnMethod": "level-up"
        },
        {
            "name": "Lunar Dance",
            "learnMethod": "level-up"
        },
        {
            "name": "Mist",
            "learnMethod": "level-up"
        },
        {
            "name": "Moonblast",
            "learnMethod": "level-up"
        },
        {
            "name": "Moonlight",
            "learnMethod": "level-up"
        },
        {
            "name": "Mud-Slap",
            "learnMethod": "machine"
        },
        {
            "name": "Power Gem",
            "learnMethod": "machine"
        },
        {
            "name": "Protect",
            "learnMethod": "machine"
        },
        {
            "name": "Psybeam",
            "learnMethod": "level-up"
        },
        {
            "name": "Psych Up",
            "learnMethod": "machine"
        },
        {
            "name": "Psychic",
            "learnMethod": "level-up"
        },
        {
            "name": "Psychic Terrain",
            "learnMethod": "machine"
        },
        {
            "name": "Psycho Cut",
            "learnMethod": "level-up"
        },
        {
            "name": "Psyshock",
            "learnMethod": "machine"
        },
        {
            "name": "Rain Dance",
            "learnMethod": "machine"
        },
        {
            "name": "Reflect",
            "learnMethod": "machine"
        },
        {
            "name": "Rest",
            "learnMethod": "machine"
        },
        {
            "name": "Safeguard",
            "learnMethod": "level-up"
        },
        {
            "name": "Scary Face",
            "learnMethod": "machine"
        },
        {
            "name": "Shadow Ball",
            "learnMethod": "machine"
        },
        {
            "name": "Skill Swap",
            "learnMethod": "machine"
        },
        {
            "name": "Slash",
            "learnMethod": "level-up"
        },
        {
            "name": "Sleep Talk",
            "learnMethod": "machine"
        },
        {
            "name": "Solar Beam",
            "learnMethod": "machine"
        },
        {
            "name": "Stored Power",
            "learnMethod": "machine"
        },
        {
            "name": "Substitute",
            "learnMethod": "machine"
        },
        {
            "name": "Sunny Day",
            "learnMethod": "machine"
        },
        {
            "name": "Swift",
            "learnMethod": "machine"
        },
        {
            "name": "Tera Blast",
            "learnMethod": "machine"
        },
        {
            "name": "Thunder",
            "learnMethod": "machine"
        },
        {
            "name": "Thunder Wave",
            "learnMethod": "machine"
        },
        {
            "name": "Thunderbolt",
            "learnMethod": "machine"
        },
        {
            "name": "Trick",
            "learnMethod": "machine"
        },
        {
            "name": "Trick Room",
            "learnMethod": "machine"
        },
        {
            "name": "Zen Headbutt",
            "learnMethod": "machine"
        }
    ]
}