{
    "name": "Kricketot",
    "abilities": [
        {
            "name": "Shed Skin",
            "hidden": false
        },
        {
            "name": "Run Away",
            "hidden": true
        }
    ],
    "types": [
        "Bug"
    ],
    "stats": {
        "hp": 37,
        "atk": 25,
        "def": 41,
        "spa": 25,
        "spd": 41,
        "spe": 25
    },
    "weightkg": 2.2,
    "nfe": true,
    "gender": null,
    "moves": [
        {
            "name": "Bug Bite",
            "learnMethod": "level-up"
        },
        {
            "name": "Endeavor",
            "learnMethod": "machine"
        },
        {
            "name": "Growl",
            "learnMethod": "level-up"
        },
        {
            "name": "Lunge",
            "learnMethod": "machine"
        },
        {
            "name": "Skitter Smack",
            "learnMethod": "machine"
        },
        {
            "name": "Struggle Bug",
            "learnMethod": "level-up"
        },
        {
            "name": "Tackle",
            "learnMethod": "level-up"
        },
        {
            "name": "Tera Blast",
            "learnMethod": "machine"
        }
    ]
}