{
    "name": "Linoone-Galar",
    "abilities": [
        {
            "name": "Pickup",
            "hidden": false
        },
        {
            "name": "Gluttony",
            "hidden": false
        },
        {
            "name": "Quick Feet",
            "hidden": true
        }
    ],
    "types": [
        "dark",
        "normal"
    ],
    "stats": {
        "hp": 78,
        "atk": 70,
        "def": 61,
        "spa": 50,
        "spd": 61,
        "spe": 100
    },
    "moves": [
    ]
}