{
    "name": "Spheal",
    "abilities": [
        {
            "name": "Thick Fat",
            "hidden": false
        },
        {
            "name": "Ice Body",
            "hidden": false
        },
        {
            "name": "Oblivious",
            "hidden": true
        }
    ],
    "types": [
        "ice",
        "water"
    ],
    "stats": {
        "hp": 70,
        "atk": 40,
        "def": 50,
        "spa": 55,
        "spd": 50,
        "spe": 25
    },
    "moves": [
    ]
}