{
    "name": "Tomohawk",
    "abilities": [
        {
            "name": "Intimidate",
            "hidden": false
        },
        {
            "name": "Prankster",
            "hidden": false
        },
        {
            "name": "Justified",
            "hidden": true
        }
    ],
    "types": [
        "flying",
        "fighting"
    ],
    "stats": {
        "hp": 105,
        "atk": 60,
        "def": 90,
        "spa": 115,
        "spd": 80,
        "spe": 85
    },
    "moves": [
        {
            "name": "Acrobatics",
            "learnMethod": "machine"
        },
        {
            "name": "Aerial Ace",
            "learnMethod": "level-up"
        },
        {
            "name": "Air Cutter",
            "learnMethod": "machine"
        },
        {
            "name": "Air Slash",
            "learnMethod": "level-up"
        },
        {
            "name": "Aura Sphere",
            "learnMethod": "level-up"
        },
        {
            "name": "Baton Pass",
            "learnMethod": "machine"
        },
        {
            "name": "Body Press",
            "learnMethod": "machine"
        },
        {
            "name": "Body Slam",
            "learnMethod": "machine"
        },
        {
            "name": "Brave Bird",
            "learnMethod": "machine"
        },
        {
            "name": "Brick Break",
            "learnMethod": "level-up"
        },
        {
            "name": "Bulk Up",
            "learnMethod": "level-up"
        },
        {
            "name": "Bulldoze",
            "learnMethod": "machine"
        },
        {
            "name": "Close Combat",
            "learnMethod": "machine"
        },
        {
            "name": "Confuse Ray",
            "learnMethod": "machine"
        },
        {
            "name": "Dual Wingbeat",
            "learnMethod": "machine"
        },
        {
            "name": "Earthquake",
            "learnMethod": "machine"
        },
        {
            "name": "Endure",
            "learnMethod": "machine"
        },
        {
            "name": "Facade",
            "learnMethod": "machine"
        },
        {
            "name": "False Swipe",
            "learnMethod": "machine"
        },
        {
            "name": "Fling",
            "learnMethod": "machine"
        },
        {
            "name": "Fly",
            "learnMethod": "machine"
        },
        {
            "name": "Focus Blast",
            "learnMethod": "machine"
        },
        {
            "name": "Focus Energy",
            "learnMethod": "level-up"
        },
        {
            "name": "Fury Swipes",
            "learnMethod": "level-up"
        },
        {
            "name": "Giga Impact",
            "learnMethod": "machine"
        },
        {
            "name": "Grass Knot",
            "learnMethod": "machine"
        },
        {
            "name": "Harden",
            "learnMethod": "level-up"
        },
        {
            "name": "Haze",
            "learnMethod": "machine"
        },
        {
            "name": "Healing Wish",
            "learnMethod": "level-up"
        },
        {
            "name": "Heat Wave",
            "learnMethod": "machine"
        },
        {
            "name": "Helping Hand",
            "learnMethod": "machine"
        },
        {
            "name": "Hurricane",
            "learnMethod": "level-up"
        },
        {
            "name": "Hyper Beam",
            "learnMethod": "machine"
        },
        {
            "name": "Hyper Voice",
            "learnMethod": "level-up"
        },
        {
            "name": "Memento",
            "learnMethod": "egg"
        },
        {
            "name": "Morning Sun",
            "learnMethod": "level-up"
        },
        {
            "name": "Mud-Slap",
            "learnMethod": "prior-evo"
        },
        {
            "name": "Protect",
            "learnMethod": "machine"
        },
        {
            "name": "Quash",
            "learnMethod": "egg"
        },
        {
            "name": "Rain Dance",
            "learnMethod": "level-up"
        },
        {
            "name": "Rapid Spin",
            "learnMethod": "egg"
        },
        {
            "name": "Rest",
            "learnMethod": "level-up"
        },
        {
            "name": "Retaliate",
            "learnMethod": "level-up"
        },
        {
            "name": "Reversal",
            "learnMethod": "machine"
        },
        {
            "name": "Roar",
            "learnMethod": "level-up"
        },
        {
            "name": "Rock Slide",
            "learnMethod": "machine"
        },
        {
            "name": "Rock Smash",
            "learnMethod": "level-up"
        },
        {
            "name": "Rock Tomb",
            "learnMethod": "machine"
        },
        {
            "name": "Roost",
            "learnMethod": "level-up"
        },
        {
            "name": "Scratch",
            "learnMethod": "level-up"
        },
        {
            "name": "Sky Attack",
            "learnMethod": "level-up"
        },
        {
            "name": "Sleep Talk",
            "learnMethod": "machine"
        },
        {
            "name": "Solar Beam",
            "learnMethod": "machine"
        },
        {
            "name": "Stealth Rock",
            "learnMethod": "machine"
        },
        {
            "name": "Stone Edge",
            "learnMethod": "machine"
        },
        {
            "name": "Substitute",
            "learnMethod": "machine"
        },
        {
            "name": "Sunny Day",
            "learnMethod": "level-up"
        },
        {
            "name": "Superpower",
            "learnMethod": "level-up"
        },
        {
            "name": "Take Down",
            "learnMethod": "machine"
        },
        {
            "name": "Taunt",
            "learnMethod": "level-up"
        },
        {
            "name": "Tera Blast",
            "learnMethod": "machine"
        },
        {
            "name": "Thief",
            "learnMethod": "machine"
        },
        {
            "name": "Trailblaze",
            "learnMethod": "machine"
        },
        {
            "name": "Whirlwind",
            "learnMethod": "level-up"
        },
        {
            "name": "Work Up",
            "learnMethod": "level-up"
        },
        {
            "name": "Yawn",
            "learnMethod": "egg"
        }
    ]
}