{
    "name": "Trevenant",
    "abilities": [
        {
            "name": "Natural Cure",
            "hidden": false
        },
        {
            "name": "Frisk",
            "hidden": false
        },
        {
            "name": "Harvest",
            "hidden": true
        }
    ],
    "types": [
        "ghost",
        "grass"
    ],
    "stats": {
        "hp": 85,
        "atk": 110,
        "def": 76,
        "spa": 65,
        "spd": 82,
        "spe": 56
    },
    "moves": [
    ]
}