{
    "name": "Iron Tail",
    "moveCategory": "Physical",
    "category": "damage+lower",
    "target": "selected-pokemon",
    "type": "Steel",
    "power": 100,
    "accuracy": 75,
    "priority": 0,
    "drain": null,
    "healing": null,
    "selfDamage": null,
    "ailment": null,
    "statChanges": [
        {
            "stat": "def",
            "change": -1
        }
    ],
    "flinchChance": null,
    "statChance": 30,
    "ailmentChance": null,
    "minHits": null,
    "maxHits": null,
    "pp": 15,
    "ignoreDefensive": false,
    "breaksProtect": false,
    "bypassSub": false,
    "makesContact": true,
    "willCrit": false,
    "highCritChance": false,
    "isPunch": false,
    "isBite": false,
    "isBullet": false,
    "isSound": false,
    "isPulse": false,
    "isSlicing": false,
    "isWind": false
}